./LICENSE
./PKG-INFO
./README.md
./cleaner.py
./pyproject.toml
./.idea/.gitignore
./.idea/downloads-folder-cleaner.iml
./.idea/misc.xml
./.idea/modules.xml
./.idea/workspace.xml
./.idea/inspectionProfiles/profiles_settings.xml
cdhl-0.1.2.dist-info/METADATA
cdhl-0.1.2.dist-info/WHEEL
cdhl-0.1.2.dist-info/entry_points.txt
cdhl-0.1.2.dist-info/licenses/LICENSE
cdhl-0.1.2.dist-info/RECORD
