Metadata-Version: 2.4
Name: CDHL
Version: 0.1.2
Summary: Automation tool that cleans up Downloads folder and places items in appropriate locations
Project-URL: Homepage, https://github.com/thelazybastard/CDHL
Project-URL: Issues, https://github.com/thelazybastard/CDHL/issues
Author-email: thelazybastard <0q2m4o1uq@mozmail.com>
License: MIT
License-File: LICENSE
Keywords: cli,tool
Classifier: License :: OSI Approved :: MIT License
Classifier: Operating System :: OS Independent
Classifier: Programming Language :: Python :: 3
Requires-Python: >=3.9
